umcu_ai_utils/__init__.py
umcu_ai_utils/database_connection.py
umcu_ai_utils/default.mplstyle
umcu_ai_utils-0.2.4.dist-info/WHEEL
umcu_ai_utils-0.2.4.dist-info/METADATA
umcu_ai_utils-0.2.4.dist-info/RECORD
