Metadata-Version: 2.3
Name: umcu-ai-utils
Version: 0.2.4
Summary: Utility functions used by multiple AI projects at the UMCU
Author: AI for Health
Author-email: AI for Health <r.peters-7@umcutrecht.nl>
Classifier: Programming Language :: Python :: 3
Classifier: Operating System :: OS Independent
Requires-Python: >=3.11
